aopc/__init__.py
aopc/main.py
aopc/methods.py
aopc-0.1.0.dist-info/METADATA
aopc-0.1.0.dist-info/WHEEL
aopc-0.1.0.dist-info/RECORD
