Metadata-Version: 2.1
Name: aopc
Version: 0.1.0
Summary: 
Author: Joakim Edin
Author-email: je@corti.ai
Requires-Python: >=3.10,<4.0
Classifier: Programming Language :: Python :: 3
Classifier: Programming Language :: Python :: 3.10
Classifier: Programming Language :: Python :: 3.11
Classifier: Programming Language :: Python :: 3.12
Requires-Dist: datasets (>=2.20.0,<3.0.0)
Requires-Dist: loguru (>=0.7.3,<0.8.0)
Requires-Dist: numba (>=0.60.0,<0.61.0)
Requires-Dist: numpy (<2.0.0)
Requires-Dist: pydantic (>=2.7,<3.0)
Requires-Dist: pydantic-settings (>=2.2.1,<3.0.0)
Requires-Dist: torch (<2.3.0)
Requires-Dist: transformers (>=4.41.2,<5.0.0)
